Niram/__init__.py
Niram/__main__.py
Niram-1.0.4.dist-info/LICENSE
Niram-1.0.4.dist-info/METADATA
Niram-1.0.4.dist-info/WHEEL
Niram-1.0.4.dist-info/top_level.txt
Niram-1.0.4.dist-info/RECORD
