Metadata-Version: 2.1
Name: Niram
Version: 1.0.4
Summary: Simple python module to colour text
Home-page: https://github.com/aswanthabam/Niram
Author: Aswanth Vc
Author-email: no-mail@mail.no
License: UNKNOWN
Keywords: colours,change coloure,terminal colour,python colours,pip colours,change colour in terminal,vhange text colour in python
Platform: UNKNOWN
Classifier: Programming Language :: Python :: 3
Classifier: License :: OSI Approved :: MIT License
Classifier: Operating System :: OS Independent
Requires-Python: >=3.6
